{
  "profile_name": "Castlevania Circle of the Moon",
  "overrides": [
    {
      "vid": "2DC8",
      "pid": "6009",
      "_note": "8BitDo-Pro3 D-mode",
      "buttons": {
        "1": { "type": "macro", "name": "CastlevaniaDropDown" },
        "4": { "type": "macro", "name": "CastlevaniaSubWeaponAttack"  },
        "5": { "virtual": "b" }
      }
    },
    {
      "vid": "2DC8",
      "pid": "6006",
      "_note": "8BitDo-Pro2 D-mode",
      "buttons": {
        "1": { "type": "macro", "name": "CastlevaniaDropDown" },
        "4": { "type": "macro", "name": "CastlevaniaSubWeaponAttack"  },
        "5": { "virtual": "b" }
      }
    }
  ]
}
